macromol_voxelize/_voxelize.cpython-39-x86_64-linux-gnu.so
macromol_voxelize/pymol.py
macromol_voxelize/voxelize.py
macromol_voxelize/_voxelize.cc
macromol_voxelize/__init__.py
macromol_voxelize/vendored/overlap/overlap.hpp
macromol_voxelize/vendored/Eigen/Eigen/SuperLUSupport
macromol_voxelize/vendored/Eigen/Eigen/Eigenvalues
macromol_voxelize/vendored/Eigen/Eigen/StdDeque
macromol_voxelize/vendored/Eigen/Eigen/Dense
macromol_voxelize/vendored/Eigen/Eigen/QtAlignedMalloc
macromol_voxelize/vendored/Eigen/Eigen/IterativeLinearSolvers
macromol_voxelize/vendored/Eigen/Eigen/PaStiXSupport
macromol_voxelize/vendored/Eigen/Eigen/MetisSupport
macromol_voxelize/vendored/Eigen/Eigen/CholmodSupport
macromol_voxelize/vendored/Eigen/Eigen/SparseCore
macromol_voxelize/vendored/Eigen/Eigen/Geometry
macromol_voxelize/vendored/Eigen/Eigen/Cholesky
macromol_voxelize/vendored/Eigen/Eigen/Sparse
macromol_voxelize/vendored/Eigen/Eigen/SPQRSupport
macromol_voxelize/vendored/Eigen/Eigen/SparseCholesky
macromol_voxelize/vendored/Eigen/Eigen/KLUSupport
macromol_voxelize/vendored/Eigen/Eigen/OrderingMethods
macromol_voxelize/vendored/Eigen/Eigen/Core
macromol_voxelize/vendored/Eigen/Eigen/SVD
macromol_voxelize/vendored/Eigen/Eigen/QR
macromol_voxelize/vendored/Eigen/Eigen/UmfPackSupport
macromol_voxelize/vendored/Eigen/Eigen/PardisoSupport
macromol_voxelize/vendored/Eigen/Eigen/LU
macromol_voxelize/vendored/Eigen/Eigen/Eigen
macromol_voxelize/vendored/Eigen/Eigen/Householder
macromol_voxelize/vendored/Eigen/Eigen/StdList
macromol_voxelize/vendored/Eigen/Eigen/StdVector
macromol_voxelize/vendored/Eigen/Eigen/SparseLU
macromol_voxelize/vendored/Eigen/Eigen/SparseQR
macromol_voxelize/vendored/Eigen/Eigen/Jacobi
macromol_voxelize/vendored/Eigen/Eigen/src/StlSupport/StdDeque.h
macromol_voxelize/vendored/Eigen/Eigen/src/StlSupport/details.h
macromol_voxelize/vendored/Eigen/Eigen/src/StlSupport/StdVector.h
macromol_voxelize-0.10.0.dist-info/top_level.txt
macromol_voxelize-0.10.0.dist-info/METADATA
macromol_voxelize-0.10.0.dist-info/RECORD
macromol_voxelize-0.10.0.dist-info/WHEEL
macromol_voxelize-0.10.0.dist-info/licenses/LICENSE.txt
