Metadata-Version: 2.1
Name: macromol_voxelize
Version: 0.10.0
Summary: Create 3D images from atomic coordinates
Author-email: Kale Kundert <kale@thekunderts.net>
Project-URL: Documentation, https://macromol_voxelize.readthedocs.io/en/latest/
Project-URL: Version Control, https://github.com/kalekundert/macromol_voxelize
Project-URL: Bug Tracker, https://github.com/kalekundert/macromol_voxelize/issues
Project-URL: Continuous Integration, https://github.com/kalekundert/macromol_voxelize/actions
Project-URL: Test Coverage, https://coveralls.io/github/kalekundert/macromol_voxelize
Classifier: Programming Language :: Python :: 3.8
Requires-Python: ~=3.8
License-File: LICENSE.txt
Requires-Dist: numpy
Requires-Dist: polars
Requires-Dist: typing-extensions
Provides-Extra: docs
Requires-Dist: sphinx ; extra == 'docs'
Requires-Dist: sphinx-rtd-theme ; extra == 'docs'
Requires-Dist: sphinx-math-dollar ; extra == 'docs'
Requires-Dist: myst-parser ; extra == 'docs'
Provides-Extra: pymol
Requires-Dist: macromol-dataframe ; extra == 'pymol'
Requires-Dist: matplotlib ; extra == 'pymol'
Requires-Dist: pymixbox ; extra == 'pymol'
Requires-Dist: pipeline-func ; extra == 'pymol'
Provides-Extra: test
Requires-Dist: macromol-dataframe ; extra == 'test'
Requires-Dist: parametrize-from-file ; extra == 'test'
Requires-Dist: pytest ; extra == 'test'
